gym_video_streamer/__init__.py
gym_video_streamer/gymVideoStreamingWrapper.py
gym_video_streamer/setupVirtualDisplay.py
gym_video_streamer/streamer.py
gym_video_streamer-1.0.dist-info/LICENSE
gym_video_streamer-1.0.dist-info/METADATA
gym_video_streamer-1.0.dist-info/WHEEL
gym_video_streamer-1.0.dist-info/top_level.txt
gym_video_streamer-1.0.dist-info/RECORD
