Metadata-Version: 2.1
Name: gym-video-streamer
Version: 1.0
Summary: Wrapper to live stream OpenAI's gym agents training process from Google Colab to Twitch/YouTube server.
Home-page: https://github.com/dhyeythumar/gym-video-streamer
Author: Dhyey Thumar
Author-email: dhyeythumar@gmail.com
License: UNKNOWN
Keywords: OpenAI,Gym,Gym Wrapper,Video Streamer,Google Colab
Platform: UNKNOWN
Classifier: Intended Audience :: Science/Research
Classifier: Topic :: Scientific/Engineering :: Artificial Intelligence
Classifier: License :: OSI Approved :: MIT License
Classifier: Operating System :: POSIX :: Linux
Classifier: Programming Language :: Python :: 3
Classifier: Topic :: Software Development :: Libraries
Requires-Dist: gym (>=0.17.3)
Requires-Dist: pyvirtualdisplay (>=2.2)
